cpt-1.3.6.dist-info/RECORD
cpt-1.3.6.dist-info/WHEEL
cpt-1.3.6.dist-info/top_level.txt
cpt-1.3.6.dist-info/METADATA
cpt-1.3.6.dist-info/licenses/LICENSE
cpt/cpt.cpython-312-darwin.so
cpt/alphabet.cpython-312-darwin.so
cpt.dylibs/libomp.dylib
