Metadata-Version: 2.4
Name: cpt
Version: 1.3.6
Summary: Compact Prediction Tree: A Lossless Model for Accurate Sequence Prediction
Home-page: https://github.com/bluesheeptoken/CPT
Author: Louis Fruleux
Author-email: louis.fruleux1@gmail.com
License: MIT
Requires-Python: >=3.10, <4
License-File: LICENSE
Dynamic: author
Dynamic: author-email
Dynamic: description
Dynamic: description-content-type
Dynamic: home-page
Dynamic: license
Dynamic: license-file
Dynamic: requires-python
Dynamic: summary
